villain_pagination/__init__.py
villain_pagination/page.py
villain_pagination/paginator.py
villain_pagination-0.1.5.dist-info/METADATA
villain_pagination-0.1.5.dist-info/WHEEL
villain_pagination-0.1.5.dist-info/top_level.txt
villain_pagination-0.1.5.dist-info/RECORD
