Metadata-Version: 2.1
Name: villain-pagination
Version: 0.1.5
Summary: A small pagination package
Home-page: https://github.com/K-villain/villain-pagination
Author: villain
Author-email: mon2210@naver.com
License: UNKNOWN
Platform: UNKNOWN
Classifier: Programming Language :: Python :: 3
Classifier: License :: OSI Approved :: MIT License
Classifier: Operating System :: OS Independent
Requires-Python: >=3.7
Requires-Dist: fastapi (>=0.88.0)
Requires-Dist: pydantic (>=1.8.2)
Requires-Dist: starlette (>=0.14.2)
